bibly/__init__.py
bibly/client.py
bibly/sciencedirect_handler.py
bibly/scopus_handler.py
bibly/search_handler.py
bibly/springer_handler.py
bibly/utils/data_types.py
bibly-0.0.2.dist-info/licenses/LICENSE
bibly-0.0.2.dist-info/METADATA
bibly-0.0.2.dist-info/WHEEL
bibly-0.0.2.dist-info/top_level.txt
bibly-0.0.2.dist-info/RECORD
